LICENSE
MANIFEST.in
README.rst
setup.py
achievements/__init__.py
achievements/forms.py
achievements/hmodule.py
achievements/models.py
achievements/urls.py
achievements/views.py
achievements/widgets.py
achievements/migrations/0001_initial.py
achievements/migrations/__init__.py
achievements/static/achievements/simple-badge.png
achievements/static/achievements/simple-icon.png
achievements/templates/html/achievements/achievement_detail.html
achievements/templates/html/achievements/achievement_form.html
achievements/templates/html/achievements/index.html
achievements/templates/html/achievements/page.html
achievements/templates/html/achievements/prototype_detail.html
achievements/templates/html/achievements/prototype_form.html
achievements/templates/html/achievements/prototypes.html
achievements/templates/html/achievements/user.html
achievements/templates/html/achievements/tags/achievements_list.html
achievements/templates/html/achievements/tags/icon_line.html
achievements/templates/html/achievements/tags/prototypes_list.html
achievements/templates/html/achievements/tags/user_list.html
achievements/templates/html/achievements/widgets/newest.html
achievements/templatetags/__init__.py
achievements/templatetags/achievements.py
treeio_achievements.egg-info/PKG-INFO
treeio_achievements.egg-info/SOURCES.txt
treeio_achievements.egg-info/dependency_links.txt
treeio_achievements.egg-info/not-zip-safe
treeio_achievements.egg-info/top_level.txt