Metadata-Version: 1.0
Name: treeio-achievements
Version: 0.1.2
Summary: A module for treeio that lets you hand out achievements.
Home-page: http://github.com/pascalmouret/treeio-achievements
Author: Pascal Mouret
Author-email: pascal.mouret@me.com
License: BSD
Platform: OS Independent
Classifier: Development Status :: 4 - Beta
Classifier: Framework :: Django
Classifier: Intended Audience :: Developers
Classifier: License :: OSI Approved :: BSD License
Classifier: Operating System :: OS Independent
Classifier: Programming Language :: Python
Classifier: Topic :: Internet :: WWW/HTTP
